pyfrag/__init__.py
pyfrag/config.py
pyfrag/main.py
pyfrag/parser_factory.py
pyfrag/version.py
pyfrag/environment/__init__.py
pyfrag/environment/add_amspipe_env.py
pyfrag/executables/__init__.py
pyfrag/executables/adf/__init__.py
pyfrag/executables/adf/adf.py
pyfrag/executables/adf/adf_driver.py
pyfrag/executables/adf/adf_parser.py
pyfrag/executables/adf/adf_to_ams_converter.py
pyfrag/executables/adf/constants.py
pyfrag/executables/adf/errors.py
pyfrag/executables/adf/input.py
pyfrag/executables/adf/mol_handling.py
pyfrag/executables/adf/result_classes.py
"pyfrag/executables/gaussian/__init__,py"
pyfrag/executables/gaussian/gaussian.py
"pyfrag/executables/orca/__init__,py"
pyfrag/executables/orca/orca.py
"pyfrag/executables/turbomole/__init__,py"
pyfrag/executables/turbomole/turbomole.py
pyfrag-2025.101b2.dist-info/METADATA
pyfrag-2025.101b2.dist-info/WHEEL
pyfrag-2025.101b2.dist-info/entry_points.txt
pyfrag-2025.101b2.dist-info/licenses/LICENSE.md
pyfrag-2025.101b2.dist-info/RECORD
