Metadata-Version: 2.4
Name: PyFrag
Version: 2025.101b2
Summary: Automation of fragment calculations of the AMS package in quantum chemistry
Project-URL: Homepage, https://github.com/TheoChem-VU/PyFrag
Author: X. Sun, J. Poater, T. A. Hamlin, F. M. Bickelhaupt
Author-email: "S.J. Lekanne Deprez" <s.j.lekanne.deprez@vu.nl>
License-Expression: LGPL-3.0
License-File: LICENSE.md
Classifier: Development Status :: 3 - Alpha
Classifier: Intended Audience :: Science/Research
Classifier: Operating System :: OS Independent
Classifier: Programming Language :: Python :: 3 :: Only
Classifier: Programming Language :: Python :: 3.8
Classifier: Programming Language :: Python :: 3.9
Classifier: Programming Language :: Python :: 3.10
Classifier: Programming Language :: Python :: 3.11
Classifier: Programming Language :: Python :: 3.12
Classifier: Programming Language :: Python :: 3.13
Classifier: Topic :: Scientific/Engineering :: Chemistry
Requires-Python: >=3.7
Requires-Dist: numpy>=1.20.0
Requires-Dist: plams>=2024.107
